{"route_id":"CR-Needham","agency_id":"1","route_short_name":null,"route_long_name":"Needham Line","route_desc":"Commuter Rail","route_type":2,"route_url":"https://www.mbta.com/schedules/CR-Needham","route_color":"80276C","route_text_color":"FFFFFF","route_sort_order":20010,"continuous_pickup":null,"continuous_drop_off":null,"trips":[{"trip_id":"CR-501372-2602","route_id":"CR-Needham","service_id":"FLL 21-S-Su-1-S0f","trip_headsign":"South Station","trip_short_name":"2602","direction_id":1,"block_id":null,"shape_id":"9860001","wheelchair_accessible":1,"bikes_allowed":1,"stop_times":[{"id":1221998,"trip_id":"CR-501372-2602","arrival_time":"08:50:00","arrival_timestamp":31800,"departure_time":"08:50:00","departure_timestamp":31800,"stop_id":"NEC-2287","stop_sequence":110,"stop_headsign":null,"pickup_type":1,"drop_off_type":0,"continuous_pickup":null,"continuous_drop_off":null,"shape_dist_traveled":null,"timepoint":1,"stop_lat":42.35141,"stop_lon":-71.055417},{"id":1221999,"trip_id":"CR-501372-2602","arrival_time":"08:45:00","arrival_timestamp":31500,"departure_time":"08:45:00","departure_timestamp":31500,"stop_id":"NEC-2276","stop_sequence":100,"stop_headsign":null,"pickup_type":0,"drop_off_type":0,"continuous_pickup":null,"continuous_drop_off":null,"shape_dist_traveled":null,"timepoint":0,"stop_lat":42.34735,"stop_lon":-71.075727},{"id":1222000,"trip_id":"CR-501372-2602","arrival_time":"08:41:00","arrival_timestamp":31260,"departure_time":"08:41:00","departure_timestamp":31260,"stop_id":"NEC-2265","stop_sequence":90,"stop_headsign":null,"pickup_type":0,"drop_off_type":0,"continuous_pickup":null,"continuous_drop_off":null,"shape_dist_traveled":null,"timepoint":0,"stop_lat":42.336608,"stop_lon":-71.089208},{"id":1222001,"trip_id":"CR-501372-2602","arrival_time":"08:36:00","arrival_timestamp":30960,"departure_time":"08:36:00","departure_timestamp":30960,"stop_id":"NEC-2237","stop_sequence":80,"stop_headsign":null,"pickup_type":0,"drop_off_type":0,"continuous_pickup":null,"continuous_drop_off":null,"shape_dist_traveled":null,"timepoint":1,"stop_lat":42.300522,"stop_lon":-71.113686},{"id":1222002,"trip_id":"CR-501372-2602","arrival_time":"08:33:00","arrival_timestamp":30780,"departure_time":"08:33:00","departure_timestamp":30780,"stop_id":"NB-0064-S","stop_sequence":70,"stop_headsign":null,"pickup_type":0,"drop_off_type":0,"continuous_pickup":null,"continuous_drop_off":null,"shape_dist_traveled":null,"timepoint":1,"stop_lat":42.287442,"stop_lon":-71.130283},{"id":1222003,"trip_id":"CR-501372-2602","arrival_time":"08:30:00","arrival_timestamp":30600,"departure_time":"08:30:00","departure_timestamp":30600,"stop_id":"NB-0072-S","stop_sequence":60,"stop_headsign":null,"pickup_type":0,"drop_off_type":0,"continuous_pickup":null,"continuous_drop_off":null,"shape_dist_traveled":null,"timepoint":1,"stop_lat":42.286588,"stop_lon":-71.145557},{"id":1222004,"trip_id":"CR-501372-2602","arrival_time":"08:28:00","arrival_timestamp":30480,"departure_time":"08:28:00","departure_timestamp":30480,"stop_id":"NB-0076-S","stop_sequence":50,"stop_headsign":null,"pickup_type":0,"drop_off_type":0,"continuous_pickup":null,"continuous_drop_off":null,"shape_dist_traveled":null,"timepoint":1,"stop_lat":42.284969,"stop_lon":-71.153937},{"id":1222005,"trip_id":"CR-501372-2602","arrival_time":"08:26:00","arrival_timestamp":30360,"departure_time":"08:26:00","departure_timestamp":30360,"stop_id":"NB-0080-S","stop_sequence":40,"stop_headsign":null,"pickup_type":0,"drop_off_type":0,"continuous_pickup":null,"continuous_drop_off":null,"shape_dist_traveled":null,"timepoint":1,"stop_lat":42.281358,"stop_lon":-71.160065},{"id":1222006,"trip_id":"CR-501372-2602","arrival_time":"08:21:00","arrival_timestamp":30060,"departure_time":"08:21:00","departure_timestamp":30060,"stop_id":"NB-0109-S","stop_sequence":30,"stop_headsign":null,"pickup_type":0,"drop_off_type":0,"continuous_pickup":null,"continuous_drop_off":null,"shape_dist_traveled":null,"timepoint":1,"stop_lat":42.275648,"stop_lon":-71.215528},{"id":1222007,"trip_id":"CR-501372-2602","arrival_time":"08:18:00","arrival_timestamp":29880,"departure_time":"08:18:00","departure_timestamp":29880,"stop_id":"NB-0120-S","stop_sequence":20,"stop_headsign":null,"pickup_type":0,"drop_off_type":0,"continuous_pickup":null,"continuous_drop_off":null,"shape_dist_traveled":null,"timepoint":1,"stop_lat":42.273187,"stop_lon":-71.235559},{"id":1222008,"trip_id":"CR-501372-2602","arrival_time":"08:14:00","arrival_timestamp":29640,"departure_time":"08:14:00","departure_timestamp":29640,"stop_id":"NB-0127-S","stop_sequence":10,"stop_headsign":null,"pickup_type":0,"drop_off_type":0,"continuous_pickup":null,"continuous_drop_off":null,"shape_dist_traveled":null,"timepoint":1,"stop_lat":42.280775,"stop_lon":-71.237686},{"id":1222009,"trip_id":"CR-501372-2602","arrival_time":"08:10:00","arrival_timestamp":29400,"departure_time":"08:10:00","departure_timestamp":29400,"stop_id":"NB-0137-S","stop_sequence":0,"stop_headsign":null,"pickup_type":0,"drop_off_type":1,"continuous_pickup":null,"continuous_drop_off":null,"shape_dist_traveled":null,"timepoint":1,"stop_lat":42.293444,"stop_lon":-71.236027}]},{"trip_id":"CR-501366-2604","route_id":"CR-Needham","service_id":"FLL 21-S-Su-1-S0f","trip_headsign":"South Station","trip_short_name":"2604","direction_id":1,"block_id":null,"shape_id":"9860001","wheelchair_accessible":1,"bikes_allowed":1,"stop_times":[{"id":1221926,"trip_id":"CR-501366-2604","arrival_time":"10:50:00","arrival_timestamp":39000,"departure_time":"10:50:00","departure_timestamp":39000,"stop_id":"NEC-2287","stop_sequence":110,"stop_headsign":null,"pickup_type":1,"drop_off_type":0,"continuous_pickup":null,"continuous_drop_off":null,"shape_dist_traveled":null,"timepoint":1,"stop_lat":42.35141,"stop_lon":-71.055417},{"id":1221927,"trip_id":"CR-501366-2604","arrival_time":"10:45:00","arrival_timestamp":38700,"departure_time":"10:45:00","departure_timestamp":38700,"stop_id":"NEC-2276","stop_sequence":100,"stop_headsign":null,"pickup_type":0,"drop_off_type":0,"continuous_pickup":null,"continuous_drop_off":null,"shape_dist_traveled":null,"timepoint":0,"stop_lat":42.34735,"stop_lon":-71.075727},{"id":1221928,"trip_id":"CR-501366-2604","arrival_time":"10:41:00","arrival_timestamp":38460,"departure_time":"10:41:00","departure_timestamp":38460,"stop_id":"NEC-2265","stop_sequence":90,"stop_headsign":null,"pickup_type":0,"drop_off_type":0,"continuous_pickup":null,"continuous_drop_off":null,"shape_dist_traveled":null,"timepoint":0,"stop_lat":42.336608,"stop_lon":-71.089208},{"id":1221929,"trip_id":"CR-501366-2604","arrival_time":"10:36:00","arrival_timestamp":38160,"departure_time":"10:36:00","departure_timestamp":38160,"stop_id":"NEC-2237","stop_sequence":80,"stop_headsign":null,"pickup_type":0,"drop_off_type":0,"continuous_pickup":null,"continuous_drop_off":null,"shape_dist_traveled":null,"timepoint":1,"stop_lat":42.300522,"stop_lon":-71.113686},{"id":1221930,"trip_id":"CR-501366-2604","arrival_time":"10:33:00","arrival_timestamp":37980,"departure_time":"10:33:00","departure_timestamp":37980,"stop_id":"NB-0064-S","stop_sequence":70,"stop_headsign":null,"pickup_type":0,"drop_off_type":0,"continuous_pickup":null,"continuous_drop_off":null,"shape_dist_traveled":null,"timepoint":1,"stop_lat":42.287442,"stop_lon":-71.130283},{"id":1221931,"trip_id":"CR-501366-2604","arrival_time":"10:30:00","arrival_timestamp":37800,"departure_time":"10:30:00","departure_timestamp":37800,"stop_id":"NB-0072-S","stop_sequence":60,"stop_headsign":null,"pickup_type":0,"drop_off_type":0,"continuous_pickup":null,"continuous_drop_off":null,"shape_dist_traveled":null,"timepoint":1,"stop_lat":42.286588,"stop_lon":-71.145557},{"id":1221932,"trip_id":"CR-501366-2604","arrival_time":"10:28:00","arrival_timestamp":37680,"departure_time":"10:28:00","departure_timestamp":37680,"stop_id":"NB-0076-S","stop_sequence":50,"stop_headsign":null,"pickup_type":0,"drop_off_type":0,"continuous_pickup":null,"continuous_drop_off":null,"shape_dist_traveled":null,"timepoint":1,"stop_lat":42.284969,"stop_lon":-71.153937},{"id":1221933,"trip_id":"CR-501366-2604","arrival_time":"10:26:00","arrival_timestamp":37560,"departure_time":"10:26:00","departure_timestamp":37560,"stop_id":"NB-0080-S","stop_sequence":40,"stop_headsign":null,"pickup_type":0,"drop_off_type":0,"continuous_pickup":null,"continuous_drop_off":null,"shape_dist_traveled":null,"timepoint":1,"stop_lat":42.281358,"stop_lon":-71.160065},{"id":1221934,"trip_id":"CR-501366-2604","arrival_time":"10:21:00","arrival_timestamp":37260,"departure_time":"10:21:00","departure_timestamp":37260,"stop_id":"NB-0109-S","stop_sequence":30,"stop_headsign":null,"pickup_type":0,"drop_off_type":0,"continuous_pickup":null,"continuous_drop_off":null,"shape_dist_traveled":null,"timepoint":1,"stop_lat":42.275648,"stop_lon":-71.215528},{"id":1221935,"trip_id":"CR-501366-2604","arrival_time":"10:18:00","arrival_timestamp":37080,"departure_time":"10:18:00","departure_timestamp":37080,"stop_id":"NB-0120-S","stop_sequence":20,"stop_headsign":null,"pickup_type":0,"drop_off_type":0,"continuous_pickup":null,"continuous_drop_off":null,"shape_dist_traveled":null,"timepoint":1,"stop_lat":42.273187,"stop_lon":-71.235559},{"id":1221936,"trip_id":"CR-501366-2604","arrival_time":"10:14:00","arrival_timestamp":36840,"departure_time":"10:14:00","departure_timestamp":36840,"stop_id":"NB-0127-S","stop_sequence":10,"stop_headsign":null,"pickup_type":0,"drop_off_type":0,"continuous_pickup":null,"continuous_drop_off":null,"shape_dist_traveled":null,"timepoint":1,"stop_lat":42.280775,"stop_lon":-71.237686},{"id":1221937,"trip_id":"CR-501366-2604","arrival_time":"10:10:00","arrival_timestamp":36600,"departure_time":"10:10:00","departure_timestamp":36600,"stop_id":"NB-0137-S","stop_sequence":0,"stop_headsign":null,"pickup_type":0,"drop_off_type":1,"continuous_pickup":null,"continuous_drop_off":null,"shape_dist_traveled":null,"timepoint":1,"stop_lat":42.293444,"stop_lon":-71.236027}]},{"trip_id":"CR-501364-2606","route_id":"CR-Needham","service_id":"FLL 21-S-Su-1-S0f","trip_headsign":"South Station","trip_short_name":"2606","direction_id":1,"block_id":null,"shape_id":"9860001","wheelchair_accessible":1,"bikes_allowed":1,"stop_times":[{"id":1221950,"trip_id":"CR-501364-2606","arrival_time":"12:50:00","arrival_timestamp":46200,"departure_time":"12:50:00","departure_timestamp":46200,"stop_id":"NEC-2287","stop_sequence":110,"stop_headsign":null,"pickup_type":1,"drop_off_type":0,"continuous_pickup":null,"continuous_drop_off":null,"shape_dist_traveled":null,"timepoint":1,"stop_lat":42.35141,"stop_lon":-71.055417},{"id":1221951,"trip_id":"CR-501364-2606","arrival_time":"12:45:00","arrival_timestamp":45900,"departure_time":"12:45:00","departure_timestamp":45900,"stop_id":"NEC-2276","stop_sequence":100,"stop_headsign":null,"pickup_type":0,"drop_off_type":0,"continuous_pickup":null,"continuous_drop_off":null,"shape_dist_traveled":null,"timepoint":0,"stop_lat":42.34735,"stop_lon":-71.075727},{"id":1221952,"trip_id":"CR-501364-2606","arrival_time":"12:41:00","arrival_timestamp":45660,"departure_time":"12:41:00","departure_timestamp":45660,"stop_id":"NEC-2265","stop_sequence":90,"stop_headsign":null,"pickup_type":0,"drop_off_type":0,"continuous_pickup":null,"continuous_drop_off":null,"shape_dist_traveled":null,"timepoint":0,"stop_lat":42.336608,"stop_lon":-71.089208},{"id":1221953,"trip_id":"CR-501364-2606","arrival_time":"12:36:00","arrival_timestamp":45360,"departure_time":"12:36:00","departure_timestamp":45360,"stop_id":"NEC-2237","stop_sequence":80,"stop_headsign":null,"pickup_type":0,"drop_off_type":0,"continuous_pickup":null,"continuous_drop_off":null,"shape_dist_traveled":null,"timepoint":1,"stop_lat":42.300522,"stop_lon":-71.113686},{"id":1221954,"trip_id":"CR-501364-2606","arrival_time":"12:33:00","arrival_timestamp":45180,"departure_time":"12:33:00","departure_timestamp":45180,"stop_id":"NB-0064-S","stop_sequence":70,"stop_headsign":null,"pickup_type":0,"drop_off_type":0,"continuous_pickup":null,"continuous_drop_off":null,"shape_dist_traveled":null,"timepoint":1,"stop_lat":42.287442,"stop_lon":-71.130283},{"id":1221955,"trip_id":"CR-501364-2606","arrival_time":"12:30:00","arrival_timestamp":45000,"departure_time":"12:30:00","departure_timestamp":45000,"stop_id":"NB-0072-S","stop_sequence":60,"stop_headsign":null,"pickup_type":0,"drop_off_type":0,"continuous_pickup":null,"continuous_drop_off":null,"shape_dist_traveled":null,"timepoint":1,"stop_lat":42.286588,"stop_lon":-71.145557},{"id":1221956,"trip_id":"CR-501364-2606","arrival_time":"12:28:00","arrival_timestamp":44880,"departure_time":"12:28:00","departure_timestamp":44880,"stop_id":"NB-0076-S","stop_sequence":50,"stop_headsign":null,"pickup_type":0,"drop_off_type":0,"continuous_pickup":null,"continuous_drop_off":null,"shape_dist_traveled":null,"timepoint":1,"stop_lat":42.284969,"stop_lon":-71.153937},{"id":1221957,"trip_id":"CR-501364-2606","arrival_time":"12:26:00","arrival_timestamp":44760,"departure_time":"12:26:00","departure_timestamp":44760,"stop_id":"NB-0080-S","stop_sequence":40,"stop_headsign":null,"pickup_type":0,"drop_off_type":0,"continuous_pickup":null,"continuous_drop_off":null,"shape_dist_traveled":null,"timepoint":1,"stop_lat":42.281358,"stop_lon":-71.160065},{"id":1221958,"trip_id":"CR-501364-2606","arrival_time":"12:21:00","arrival_timestamp":44460,"departure_time":"12:21:00","departure_timestamp":44460,"stop_id":"NB-0109-S","stop_sequence":30,"stop_headsign":null,"pickup_type":0,"drop_off_type":0,"continuous_pickup":null,"continuous_drop_off":null,"shape_dist_traveled":null,"timepoint":1,"stop_lat":42.275648,"stop_lon":-71.215528},{"id":1221959,"trip_id":"CR-501364-2606","arrival_time":"12:18:00","arrival_timestamp":44280,"departure_time":"12:18:00","departure_timestamp":44280,"stop_id":"NB-0120-S","stop_sequence":20,"stop_headsign":null,"pickup_type":0,"drop_off_type":0,"continuous_pickup":null,"continuous_drop_off":null,"shape_dist_traveled":null,"timepoint":1,"stop_lat":42.273187,"stop_lon":-71.235559},{"id":1221960,"trip_id":"CR-501364-2606","arrival_time":"12:14:00","arrival_timestamp":44040,"departure_time":"12:14:00","departure_timestamp":44040,"stop_id":"NB-0127-S","stop_sequence":10,"stop_headsign":null,"pickup_type":0,"drop_off_type":0,"continuous_pickup":null,"continuous_drop_off":null,"shape_dist_traveled":null,"timepoint":1,"stop_lat":42.280775,"stop_lon":-71.237686},{"id":1221961,"trip_id":"CR-501364-2606","arrival_time":"12:10:00","arrival_timestamp":43800,"departure_time":"12:10:00","departure_timestamp":43800,"stop_id":"NB-0137-S","stop_sequence":0,"stop_headsign":null,"pickup_type":0,"drop_off_type":1,"continuous_pickup":null,"continuous_drop_off":null,"shape_dist_traveled":null,"timepoint":1,"stop_lat":42.293444,"stop_lon":-71.236027}]},{"trip_id":"CR-501362-2608","route_id":"CR-Needham","service_id":"FLL 21-S-Su-1-S0f","trip_headsign":"South Station","trip_short_name":"2608","direction_id":1,"block_id":null,"shape_id":"9860001","wheelchair_accessible":1,"bikes_allowed":1,"stop_times":[{"id":1221866,"trip_id":"CR-501362-2608","arrival_time":"14:50:00","arrival_timestamp":53400,"departure_time":"14:50:00","departure_timestamp":53400,"stop_id":"NEC-2287","stop_sequence":110,"stop_headsign":null,"pickup_type":1,"drop_off_type":0,"continuous_pickup":null,"continuous_drop_off":null,"shape_dist_traveled":null,"timepoint":1,"stop_lat":42.35141,"stop_lon":-71.055417},{"id":1221867,"trip_id":"CR-501362-2608","arrival_time":"14:45:00","arrival_timestamp":53100,"departure_time":"14:45:00","departure_timestamp":53100,"stop_id":"NEC-2276","stop_sequence":100,"stop_headsign":null,"pickup_type":0,"drop_off_type":0,"continuous_pickup":null,"continuous_drop_off":null,"shape_dist_traveled":null,"timepoint":0,"stop_lat":42.34735,"stop_lon":-71.075727},{"id":1221868,"trip_id":"CR-501362-2608","arrival_time":"14:41:00","arrival_timestamp":52860,"departure_time":"14:41:00","departure_timestamp":52860,"stop_id":"NEC-2265","stop_sequence":90,"stop_headsign":null,"pickup_type":0,"drop_off_type":0,"continuous_pickup":null,"continuous_drop_off":null,"shape_dist_traveled":null,"timepoint":0,"stop_lat":42.336608,"stop_lon":-71.089208},{"id":1221869,"trip_id":"CR-501362-2608","arrival_time":"14:36:00","arrival_timestamp":52560,"departure_time":"14:36:00","departure_timestamp":52560,"stop_id":"NEC-2237","stop_sequence":80,"stop_headsign":null,"pickup_type":0,"drop_off_type":0,"continuous_pickup":null,"continuous_drop_off":null,"shape_dist_traveled":null,"timepoint":1,"stop_lat":42.300522,"stop_lon":-71.113686},{"id":1221870,"trip_id":"CR-501362-2608","arrival_time":"14:33:00","arrival_timestamp":52380,"departure_time":"14:33:00","departure_timestamp":52380,"stop_id":"NB-0064-S","stop_sequence":70,"stop_headsign":null,"pickup_type":0,"drop_off_type":0,"continuous_pickup":null,"continuous_drop_off":null,"shape_dist_traveled":null,"timepoint":1,"stop_lat":42.287442,"stop_lon":-71.130283},{"id":1221871,"trip_id":"CR-501362-2608","arrival_time":"14:30:00","arrival_timestamp":52200,"departure_time":"14:30:00","departure_timestamp":52200,"stop_id":"NB-0072-S","stop_sequence":60,"stop_headsign":null,"pickup_type":0,"drop_off_type":0,"continuous_pickup":null,"continuous_drop_off":null,"shape_dist_traveled":null,"timepoint":1,"stop_lat":42.286588,"stop_lon":-71.145557},{"id":1221872,"trip_id":"CR-501362-2608","arrival_time":"14:28:00","arrival_timestamp":52080,"departure_time":"14:28:00","departure_timestamp":52080,"stop_id":"NB-0076-S","stop_sequence":50,"stop_headsign":null,"pickup_type":0,"drop_off_type":0,"continuous_pickup":null,"continuous_drop_off":null,"shape_dist_traveled":null,"timepoint":1,"stop_lat":42.284969,"stop_lon":-71.153937},{"id":1221873,"trip_id":"CR-501362-2608","arrival_time":"14:26:00","arrival_timestamp":51960,"departure_time":"14:26:00","departure_timestamp":51960,"stop_id":"NB-0080-S","stop_sequence":40,"stop_headsign":null,"pickup_type":0,"drop_off_type":0,"continuous_pickup":null,"continuous_drop_off":null,"shape_dist_traveled":null,"timepoint":1,"stop_lat":42.281358,"stop_lon":-71.160065},{"id":1221874,"trip_id":"CR-501362-2608","arrival_time":"14:21:00","arrival_timestamp":51660,"departure_time":"14:21:00","departure_timestamp":51660,"stop_id":"NB-0109-S","stop_sequence":30,"stop_headsign":null,"pickup_type":0,"drop_off_type":0,"continuous_pickup":null,"continuous_drop_off":null,"shape_dist_traveled":null,"timepoint":1,"stop_lat":42.275648,"stop_lon":-71.215528},{"id":1221875,"trip_id":"CR-501362-2608","arrival_time":"14:18:00","arrival_timestamp":51480,"departure_time":"14:18:00","departure_timestamp":51480,"stop_id":"NB-0120-S","stop_sequence":20,"stop_headsign":null,"pickup_type":0,"drop_off_type":0,"continuous_pickup":null,"continuous_drop_off":null,"shape_dist_traveled":null,"timepoint":1,"stop_lat":42.273187,"stop_lon":-71.235559},{"id":1221876,"trip_id":"CR-501362-2608","arrival_time":"14:14:00","arrival_timestamp":51240,"departure_time":"14:14:00","departure_timestamp":51240,"stop_id":"NB-0127-S","stop_sequence":10,"stop_headsign":null,"pickup_type":0,"drop_off_type":0,"continuous_pickup":null,"continuous_drop_off":null,"shape_dist_traveled":null,"timepoint":1,"stop_lat":42.280775,"stop_lon":-71.237686},{"id":1221877,"trip_id":"CR-501362-2608","arrival_time":"14:10:00","arrival_timestamp":51000,"departure_time":"14:10:00","departure_timestamp":51000,"stop_id":"NB-0137-S","stop_sequence":0,"stop_headsign":null,"pickup_type":0,"drop_off_type":1,"continuous_pickup":null,"continuous_drop_off":null,"shape_dist_traveled":null,"timepoint":1,"stop_lat":42.293444,"stop_lon":-71.236027}]},{"trip_id":"CR-501360-2614","route_id":"CR-Needham","service_id":"FLL 21-S-Su-1-S0f","trip_headsign":"South Station","trip_short_name":"2614","direction_id":1,"block_id":null,"shape_id":"9860001","wheelchair_accessible":1,"bikes_allowed":1,"stop_times":[{"id":1221890,"trip_id":"CR-501360-2614","arrival_time":"20:50:00","arrival_timestamp":75000,"departure_time":"20:50:00","departure_timestamp":75000,"stop_id":"NEC-2287","stop_sequence":110,"stop_headsign":null,"pickup_type":1,"drop_off_type":0,"continuous_pickup":null,"continuous_drop_off":null,"shape_dist_traveled":null,"timepoint":1,"stop_lat":42.35141,"stop_lon":-71.055417},{"id":1221891,"trip_id":"CR-501360-2614","arrival_time":"20:45:00","arrival_timestamp":74700,"departure_time":"20:45:00","departure_timestamp":74700,"stop_id":"NEC-2276","stop_sequence":100,"stop_headsign":null,"pickup_type":0,"drop_off_type":0,"continuous_pickup":null,"continuous_drop_off":null,"shape_dist_traveled":null,"timepoint":0,"stop_lat":42.34735,"stop_lon":-71.075727},{"id":1221892,"trip_id":"CR-501360-2614","arrival_time":"20:41:00","arrival_timestamp":74460,"departure_time":"20:41:00","departure_timestamp":74460,"stop_id":"NEC-2265","stop_sequence":90,"stop_headsign":null,"pickup_type":0,"drop_off_type":0,"continuous_pickup":null,"continuous_drop_off":null,"shape_dist_traveled":null,"timepoint":0,"stop_lat":42.336608,"stop_lon":-71.089208},{"id":1221893,"trip_id":"CR-501360-2614","arrival_time":"20:36:00","arrival_timestamp":74160,"departure_time":"20:36:00","departure_timestamp":74160,"stop_id":"NEC-2237","stop_sequence":80,"stop_headsign":null,"pickup_type":0,"drop_off_type":0,"continuous_pickup":null,"continuous_drop_off":null,"shape_dist_traveled":null,"timepoint":1,"stop_lat":42.300522,"stop_lon":-71.113686},{"id":1221894,"trip_id":"CR-501360-2614","arrival_time":"20:33:00","arrival_timestamp":73980,"departure_time":"20:33:00","departure_timestamp":73980,"stop_id":"NB-0064-S","stop_sequence":70,"stop_headsign":null,"pickup_type":0,"drop_off_type":0,"continuous_pickup":null,"continuous_drop_off":null,"shape_dist_traveled":null,"timepoint":1,"stop_lat":42.287442,"stop_lon":-71.130283},{"id":1221895,"trip_id":"CR-501360-2614","arrival_time":"20:30:00","arrival_timestamp":73800,"departure_time":"20:30:00","departure_timestamp":73800,"stop_id":"NB-0072-S","stop_sequence":60,"stop_headsign":null,"pickup_type":0,"drop_off_type":0,"continuous_pickup":null,"continuous_drop_off":null,"shape_dist_traveled":null,"timepoint":1,"stop_lat":42.286588,"stop_lon":-71.145557},{"id":1221896,"trip_id":"CR-501360-2614","arrival_time":"20:28:00","arrival_timestamp":73680,"departure_time":"20:28:00","departure_timestamp":73680,"stop_id":"NB-0076-S","stop_sequence":50,"stop_headsign":null,"pickup_type":0,"drop_off_type":0,"continuous_pickup":null,"continuous_drop_off":null,"shape_dist_traveled":null,"timepoint":1,"stop_lat":42.284969,"stop_lon":-71.153937},{"id":1221897,"trip_id":"CR-501360-2614","arrival_time":"20:26:00","arrival_timestamp":73560,"departure_time":"20:26:00","departure_timestamp":73560,"stop_id":"NB-0080-S","stop_sequence":40,"stop_headsign":null,"pickup_type":0,"drop_off_type":0,"continuous_pickup":null,"continuous_drop_off":null,"shape_dist_traveled":null,"timepoint":1,"stop_lat":42.281358,"stop_lon":-71.160065},{"id":1221898,"trip_id":"CR-501360-2614","arrival_time":"20:21:00","arrival_timestamp":73260,"departure_time":"20:21:00","departure_timestamp":73260,"stop_id":"NB-0109-S","stop_sequence":30,"stop_headsign":null,"pickup_type":0,"drop_off_type":0,"continuous_pickup":null,"continuous_drop_off":null,"shape_dist_traveled":null,"timepoint":1,"stop_lat":42.275648,"stop_lon":-71.215528},{"id":1221899,"trip_id":"CR-501360-2614","arrival_time":"20:18:00","arrival_timestamp":73080,"departure_time":"20:18:00","departure_timestamp":73080,"stop_id":"NB-0120-S","stop_sequence":20,"stop_headsign":null,"pickup_type":0,"drop_off_type":0,"continuous_pickup":null,"continuous_drop_off":null,"shape_dist_traveled":null,"timepoint":1,"stop_lat":42.273187,"stop_lon":-71.235559},{"id":1221900,"trip_id":"CR-501360-2614","arrival_time":"20:14:00","arrival_timestamp":72840,"departure_time":"20:14:00","departure_timestamp":72840,"stop_id":"NB-0127-S","stop_sequence":10,"stop_headsign":null,"pickup_type":0,"drop_off_type":0,"continuous_pickup":null,"continuous_drop_off":null,"shape_dist_traveled":null,"timepoint":1,"stop_lat":42.280775,"stop_lon":-71.237686},{"id":1221901,"trip_id":"CR-501360-2614","arrival_time":"20:10:00","arrival_timestamp":72600,"departure_time":"20:10:00","departure_timestamp":72600,"stop_id":"NB-0137-S","stop_sequence":0,"stop_headsign":null,"pickup_type":0,"drop_off_type":1,"continuous_pickup":null,"continuous_drop_off":null,"shape_dist_traveled":null,"timepoint":1,"stop_lat":42.293444,"stop_lon":-71.236027}]},{"trip_id":"CR-501358-2612","route_id":"CR-Needham","service_id":"FLL 21-S-Su-1-S0f","trip_headsign":"South Station","trip_short_name":"2612","direction_id":1,"block_id":null,"shape_id":"9860001","wheelchair_accessible":1,"bikes_allowed":1,"stop_times":[{"id":1221806,"trip_id":"CR-501358-2612","arrival_time":"18:50:00","arrival_timestamp":67800,"departure_time":"18:50:00","departure_timestamp":67800,"stop_id":"NEC-2287","stop_sequence":110,"stop_headsign":null,"pickup_type":1,"drop_off_type":0,"continuous_pickup":null,"continuous_drop_off":null,"shape_dist_traveled":null,"timepoint":1,"stop_lat":42.35141,"stop_lon":-71.055417},{"id":1221807,"trip_id":"CR-501358-2612","arrival_time":"18:45:00","arrival_timestamp":67500,"departure_time":"18:45:00","departure_timestamp":67500,"stop_id":"NEC-2276","stop_sequence":100,"stop_headsign":null,"pickup_type":0,"drop_off_type":0,"continuous_pickup":null,"continuous_drop_off":null,"shape_dist_traveled":null,"timepoint":0,"stop_lat":42.34735,"stop_lon":-71.075727},{"id":1221808,"trip_id":"CR-501358-2612","arrival_time":"18:41:00","arrival_timestamp":67260,"departure_time":"18:41:00","departure_timestamp":67260,"stop_id":"NEC-2265","stop_sequence":90,"stop_headsign":null,"pickup_type":0,"drop_off_type":0,"continuous_pickup":null,"continuous_drop_off":null,"shape_dist_traveled":null,"timepoint":0,"stop_lat":42.336608,"stop_lon":-71.089208},{"id":1221809,"trip_id":"CR-501358-2612","arrival_time":"18:36:00","arrival_timestamp":66960,"departure_time":"18:36:00","departure_timestamp":66960,"stop_id":"NEC-2237","stop_sequence":80,"stop_headsign":null,"pickup_type":0,"drop_off_type":0,"continuous_pickup":null,"continuous_drop_off":null,"shape_dist_traveled":null,"timepoint":1,"stop_lat":42.300522,"stop_lon":-71.113686},{"id":1221810,"trip_id":"CR-501358-2612","arrival_time":"18:33:00","arrival_timestamp":66780,"departure_time":"18:33:00","departure_timestamp":66780,"stop_id":"NB-0064-S","stop_sequence":70,"stop_headsign":null,"pickup_type":0,"drop_off_type":0,"continuous_pickup":null,"continuous_drop_off":null,"shape_dist_traveled":null,"timepoint":1,"stop_lat":42.287442,"stop_lon":-71.130283},{"id":1221811,"trip_id":"CR-501358-2612","arrival_time":"18:30:00","arrival_timestamp":66600,"departure_time":"18:30:00","departure_timestamp":66600,"stop_id":"NB-0072-S","stop_sequence":60,"stop_headsign":null,"pickup_type":0,"drop_off_type":0,"continuous_pickup":null,"continuous_drop_off":null,"shape_dist_traveled":null,"timepoint":1,"stop_lat":42.286588,"stop_lon":-71.145557},{"id":1221812,"trip_id":"CR-501358-2612","arrival_time":"18:28:00","arrival_timestamp":66480,"departure_time":"18:28:00","departure_timestamp":66480,"stop_id":"NB-0076-S","stop_sequence":50,"stop_headsign":null,"pickup_type":0,"drop_off_type":0,"continuous_pickup":null,"continuous_drop_off":null,"shape_dist_traveled":null,"timepoint":1,"stop_lat":42.284969,"stop_lon":-71.153937},{"id":1221813,"trip_id":"CR-501358-2612","arrival_time":"18:26:00","arrival_timestamp":66360,"departure_time":"18:26:00","departure_timestamp":66360,"stop_id":"NB-0080-S","stop_sequence":40,"stop_headsign":null,"pickup_type":0,"drop_off_type":0,"continuous_pickup":null,"continuous_drop_off":null,"shape_dist_traveled":null,"timepoint":1,"stop_lat":42.281358,"stop_lon":-71.160065},{"id":1221814,"trip_id":"CR-501358-2612","arrival_time":"18:21:00","arrival_timestamp":66060,"departure_time":"18:21:00","departure_timestamp":66060,"stop_id":"NB-0109-S","stop_sequence":30,"stop_headsign":null,"pickup_type":0,"drop_off_type":0,"continuous_pickup":null,"continuous_drop_off":null,"shape_dist_traveled":null,"timepoint":1,"stop_lat":42.275648,"stop_lon":-71.215528},{"id":1221815,"trip_id":"CR-501358-2612","arrival_time":"18:18:00","arrival_timestamp":65880,"departure_time":"18:18:00","departure_timestamp":65880,"stop_id":"NB-0120-S","stop_sequence":20,"stop_headsign":null,"pickup_type":0,"drop_off_type":0,"continuous_pickup":null,"continuous_drop_off":null,"shape_dist_traveled":null,"timepoint":1,"stop_lat":42.273187,"stop_lon":-71.235559},{"id":1221816,"trip_id":"CR-501358-2612","arrival_time":"18:14:00","arrival_timestamp":65640,"departure_time":"18:14:00","departure_timestamp":65640,"stop_id":"NB-0127-S","stop_sequence":10,"stop_headsign":null,"pickup_type":0,"drop_off_type":0,"continuous_pickup":null,"continuous_drop_off":null,"shape_dist_traveled":null,"timepoint":1,"stop_lat":42.280775,"stop_lon":-71.237686},{"id":1221817,"trip_id":"CR-501358-2612","arrival_time":"18:10:00","arrival_timestamp":65400,"departure_time":"18:10:00","departure_timestamp":65400,"stop_id":"NB-0137-S","stop_sequence":0,"stop_headsign":null,"pickup_type":0,"drop_off_type":1,"continuous_pickup":null,"continuous_drop_off":null,"shape_dist_traveled":null,"timepoint":1,"stop_lat":42.293444,"stop_lon":-71.236027}]},{"trip_id":"CR-501356-2600","route_id":"CR-Needham","service_id":"FLL 21-S-Su-1-S0f","trip_headsign":"South Station","trip_short_name":"2600","direction_id":1,"block_id":null,"shape_id":"9860001","wheelchair_accessible":1,"bikes_allowed":1,"stop_times":[{"id":1221830,"trip_id":"CR-501356-2600","arrival_time":"06:50:00","arrival_timestamp":24600,"departure_time":"06:50:00","departure_timestamp":24600,"stop_id":"NEC-2287","stop_sequence":110,"stop_headsign":null,"pickup_type":1,"drop_off_type":0,"continuous_pickup":null,"continuous_drop_off":null,"shape_dist_traveled":null,"timepoint":1,"stop_lat":42.35141,"stop_lon":-71.055417},{"id":1221831,"trip_id":"CR-501356-2600","arrival_time":"06:45:00","arrival_timestamp":24300,"departure_time":"06:45:00","departure_timestamp":24300,"stop_id":"NEC-2276","stop_sequence":100,"stop_headsign":null,"pickup_type":0,"drop_off_type":0,"continuous_pickup":null,"continuous_drop_off":null,"shape_dist_traveled":null,"timepoint":0,"stop_lat":42.34735,"stop_lon":-71.075727},{"id":1221832,"trip_id":"CR-501356-2600","arrival_time":"06:41:00","arrival_timestamp":24060,"departure_time":"06:41:00","departure_timestamp":24060,"stop_id":"NEC-2265","stop_sequence":90,"stop_headsign":null,"pickup_type":0,"drop_off_type":0,"continuous_pickup":null,"continuous_drop_off":null,"shape_dist_traveled":null,"timepoint":0,"stop_lat":42.336608,"stop_lon":-71.089208},{"id":1221833,"trip_id":"CR-501356-2600","arrival_time":"06:36:00","arrival_timestamp":23760,"departure_time":"06:36:00","departure_timestamp":23760,"stop_id":"NEC-2237","stop_sequence":80,"stop_headsign":null,"pickup_type":0,"drop_off_type":0,"continuous_pickup":null,"continuous_drop_off":null,"shape_dist_traveled":null,"timepoint":1,"stop_lat":42.300522,"stop_lon":-71.113686},{"id":1221834,"trip_id":"CR-501356-2600","arrival_time":"06:33:00","arrival_timestamp":23580,"departure_time":"06:33:00","departure_timestamp":23580,"stop_id":"NB-0064-S","stop_sequence":70,"stop_headsign":null,"pickup_type":0,"drop_off_type":0,"continuous_pickup":null,"continuous_drop_off":null,"shape_dist_traveled":null,"timepoint":1,"stop_lat":42.287442,"stop_lon":-71.130283},{"id":1221835,"trip_id":"CR-501356-2600","arrival_time":"06:30:00","arrival_timestamp":23400,"departure_time":"06:30:00","departure_timestamp":23400,"stop_id":"NB-0072-S","stop_sequence":60,"stop_headsign":null,"pickup_type":0,"drop_off_type":0,"continuous_pickup":null,"continuous_drop_off":null,"shape_dist_traveled":null,"timepoint":1,"stop_lat":42.286588,"stop_lon":-71.145557},{"id":1221836,"trip_id":"CR-501356-2600","arrival_time":"06:28:00","arrival_timestamp":23280,"departure_time":"06:28:00","departure_timestamp":23280,"stop_id":"NB-0076-S","stop_sequence":50,"stop_headsign":null,"pickup_type":0,"drop_off_type":0,"continuous_pickup":null,"continuous_drop_off":null,"shape_dist_traveled":null,"timepoint":1,"stop_lat":42.284969,"stop_lon":-71.153937},{"id":1221837,"trip_id":"CR-501356-2600","arrival_time":"06:26:00","arrival_timestamp":23160,"departure_time":"06:26:00","departure_timestamp":23160,"stop_id":"NB-0080-S","stop_sequence":40,"stop_headsign":null,"pickup_type":0,"drop_off_type":0,"continuous_pickup":null,"continuous_drop_off":null,"shape_dist_traveled":null,"timepoint":1,"stop_lat":42.281358,"stop_lon":-71.160065},{"id":1221838,"trip_id":"CR-501356-2600","arrival_time":"06:21:00","arrival_timestamp":22860,"departure_time":"06:21:00","departure_timestamp":22860,"stop_id":"NB-0109-S","stop_sequence":30,"stop_headsign":null,"pickup_type":0,"drop_off_type":0,"continuous_pickup":null,"continuous_drop_off":null,"shape_dist_traveled":null,"timepoint":1,"stop_lat":42.275648,"stop_lon":-71.215528},{"id":1221839,"trip_id":"CR-501356-2600","arrival_time":"06:18:00","arrival_timestamp":22680,"departure_time":"06:18:00","departure_timestamp":22680,"stop_id":"NB-0120-S","stop_sequence":20,"stop_headsign":null,"pickup_type":0,"drop_off_type":0,"continuous_pickup":null,"continuous_drop_off":null,"shape_dist_traveled":null,"timepoint":1,"stop_lat":42.273187,"stop_lon":-71.235559},{"id":1221840,"trip_id":"CR-501356-2600","arrival_time":"06:14:00","arrival_timestamp":22440,"departure_time":"06:14:00","departure_timestamp":22440,"stop_id":"NB-0127-S","stop_sequence":10,"stop_headsign":null,"pickup_type":0,"drop_off_type":0,"continuous_pickup":null,"continuous_drop_off":null,"shape_dist_traveled":null,"timepoint":1,"stop_lat":42.280775,"stop_lon":-71.237686},{"id":1221841,"trip_id":"CR-501356-2600","arrival_time":"06:10:00","arrival_timestamp":22200,"departure_time":"06:10:00","departure_timestamp":22200,"stop_id":"NB-0137-S","stop_sequence":0,"stop_headsign":null,"pickup_type":0,"drop_off_type":1,"continuous_pickup":null,"continuous_drop_off":null,"shape_dist_traveled":null,"timepoint":1,"stop_lat":42.293444,"stop_lon":-71.236027}]},{"trip_id":"CR-501355-2610","route_id":"CR-Needham","service_id":"FLL 21-S-Su-1-S0f","trip_headsign":"South Station","trip_short_name":"2610","direction_id":1,"block_id":null,"shape_id":"9860001","wheelchair_accessible":1,"bikes_allowed":1,"stop_times":[{"id":1221842,"trip_id":"CR-501355-2610","arrival_time":"16:50:00","arrival_timestamp":60600,"departure_time":"16:50:00","departure_timestamp":60600,"stop_id":"NEC-2287","stop_sequence":110,"stop_headsign":null,"pickup_type":1,"drop_off_type":0,"continuous_pickup":null,"continuous_drop_off":null,"shape_dist_traveled":null,"timepoint":1,"stop_lat":42.35141,"stop_lon":-71.055417},{"id":1221843,"trip_id":"CR-501355-2610","arrival_time":"16:45:00","arrival_timestamp":60300,"departure_time":"16:45:00","departure_timestamp":60300,"stop_id":"NEC-2276","stop_sequence":100,"stop_headsign":null,"pickup_type":0,"drop_off_type":0,"continuous_pickup":null,"continuous_drop_off":null,"shape_dist_traveled":null,"timepoint":0,"stop_lat":42.34735,"stop_lon":-71.075727},{"id":1221844,"trip_id":"CR-501355-2610","arrival_time":"16:41:00","arrival_timestamp":60060,"departure_time":"16:41:00","departure_timestamp":60060,"stop_id":"NEC-2265","stop_sequence":90,"stop_headsign":null,"pickup_type":0,"drop_off_type":0,"continuous_pickup":null,"continuous_drop_off":null,"shape_dist_traveled":null,"timepoint":0,"stop_lat":42.336608,"stop_lon":-71.089208},{"id":1221845,"trip_id":"CR-501355-2610","arrival_time":"16:36:00","arrival_timestamp":59760,"departure_time":"16:36:00","departure_timestamp":59760,"stop_id":"NEC-2237","stop_sequence":80,"stop_headsign":null,"pickup_type":0,"drop_off_type":0,"continuous_pickup":null,"continuous_drop_off":null,"shape_dist_traveled":null,"timepoint":1,"stop_lat":42.300522,"stop_lon":-71.113686},{"id":1221846,"trip_id":"CR-501355-2610","arrival_time":"16:33:00","arrival_timestamp":59580,"departure_time":"16:33:00","departure_timestamp":59580,"stop_id":"NB-0064-S","stop_sequence":70,"stop_headsign":null,"pickup_type":0,"drop_off_type":0,"continuous_pickup":null,"continuous_drop_off":null,"shape_dist_traveled":null,"timepoint":1,"stop_lat":42.287442,"stop_lon":-71.130283},{"id":1221847,"trip_id":"CR-501355-2610","arrival_time":"16:30:00","arrival_timestamp":59400,"departure_time":"16:30:00","departure_timestamp":59400,"stop_id":"NB-0072-S","stop_sequence":60,"stop_headsign":null,"pickup_type":0,"drop_off_type":0,"continuous_pickup":null,"continuous_drop_off":null,"shape_dist_traveled":null,"timepoint":1,"stop_lat":42.286588,"stop_lon":-71.145557},{"id":1221848,"trip_id":"CR-501355-2610","arrival_time":"16:28:00","arrival_timestamp":59280,"departure_time":"16:28:00","departure_timestamp":59280,"stop_id":"NB-0076-S","stop_sequence":50,"stop_headsign":null,"pickup_type":0,"drop_off_type":0,"continuous_pickup":null,"continuous_drop_off":null,"shape_dist_traveled":null,"timepoint":1,"stop_lat":42.284969,"stop_lon":-71.153937},{"id":1221849,"trip_id":"CR-501355-2610","arrival_time":"16:26:00","arrival_timestamp":59160,"departure_time":"16:26:00","departure_timestamp":59160,"stop_id":"NB-0080-S","stop_sequence":40,"stop_headsign":null,"pickup_type":0,"drop_off_type":0,"continuous_pickup":null,"continuous_drop_off":null,"shape_dist_traveled":null,"timepoint":1,"stop_lat":42.281358,"stop_lon":-71.160065},{"id":1221850,"trip_id":"CR-501355-2610","arrival_time":"16:21:00","arrival_timestamp":58860,"departure_time":"16:21:00","departure_timestamp":58860,"stop_id":"NB-0109-S","stop_sequence":30,"stop_headsign":null,"pickup_type":0,"drop_off_type":0,"continuous_pickup":null,"continuous_drop_off":null,"shape_dist_traveled":null,"timepoint":1,"stop_lat":42.275648,"stop_lon":-71.215528},{"id":1221851,"trip_id":"CR-501355-2610","arrival_time":"16:18:00","arrival_timestamp":58680,"departure_time":"16:18:00","departure_timestamp":58680,"stop_id":"NB-0120-S","stop_sequence":20,"stop_headsign":null,"pickup_type":0,"drop_off_type":0,"continuous_pickup":null,"continuous_drop_off":null,"shape_dist_traveled":null,"timepoint":1,"stop_lat":42.273187,"stop_lon":-71.235559},{"id":1221852,"trip_id":"CR-501355-2610","arrival_time":"16:14:00","arrival_timestamp":58440,"departure_time":"16:14:00","departure_timestamp":58440,"stop_id":"NB-0127-S","stop_sequence":10,"stop_headsign":null,"pickup_type":0,"drop_off_type":0,"continuous_pickup":null,"continuous_drop_off":null,"shape_dist_traveled":null,"timepoint":1,"stop_lat":42.280775,"stop_lon":-71.237686},{"id":1221853,"trip_id":"CR-501355-2610","arrival_time":"16:10:00","arrival_timestamp":58200,"departure_time":"16:10:00","departure_timestamp":58200,"stop_id":"NB-0137-S","stop_sequence":0,"stop_headsign":null,"pickup_type":0,"drop_off_type":1,"continuous_pickup":null,"continuous_drop_off":null,"shape_dist_traveled":null,"timepoint":1,"stop_lat":42.293444,"stop_lon":-71.236027}]},{"trip_id":"CR-508028-2615","route_id":"CR-Needham","service_id":"FLL 21-S-Su-1-S0f","trip_headsign":"Needham Heights","trip_short_name":"2615","direction_id":0,"block_id":null,"shape_id":"9860002","wheelchair_accessible":1,"bikes_allowed":1,"stop_times":[{"id":1229395,"trip_id":"CR-508028-2615","arrival_time":"22:55:00","arrival_timestamp":82500,"departure_time":"22:55:00","departure_timestamp":82500,"stop_id":"NB-0137-S","stop_sequence":110,"stop_headsign":null,"pickup_type":1,"drop_off_type":0,"continuous_pickup":null,"continuous_drop_off":null,"shape_dist_traveled":null,"timepoint":1,"stop_lat":42.293444,"stop_lon":-71.236027},{"id":1229396,"trip_id":"CR-508028-2615","arrival_time":"22:50:00","arrival_timestamp":82200,"departure_time":"22:50:00","departure_timestamp":82200,"stop_id":"NB-0127-S","stop_sequence":100,"stop_headsign":null,"pickup_type":0,"drop_off_type":0,"continuous_pickup":null,"continuous_drop_off":null,"shape_dist_traveled":null,"timepoint":1,"stop_lat":42.280775,"stop_lon":-71.237686},{"id":1229397,"trip_id":"CR-508028-2615","arrival_time":"22:46:00","arrival_timestamp":81960,"departure_time":"22:46:00","departure_timestamp":81960,"stop_id":"NB-0120-S","stop_sequence":90,"stop_headsign":null,"pickup_type":0,"drop_off_type":0,"continuous_pickup":null,"continuous_drop_off":null,"shape_dist_traveled":null,"timepoint":1,"stop_lat":42.273187,"stop_lon":-71.235559},{"id":1229398,"trip_id":"CR-508028-2615","arrival_time":"22:43:00","arrival_timestamp":81780,"departure_time":"22:43:00","departure_timestamp":81780,"stop_id":"NB-0109-S","stop_sequence":80,"stop_headsign":null,"pickup_type":0,"drop_off_type":0,"continuous_pickup":null,"continuous_drop_off":null,"shape_dist_traveled":null,"timepoint":1,"stop_lat":42.275648,"stop_lon":-71.215528},{"id":1229399,"trip_id":"CR-508028-2615","arrival_time":"22:38:00","arrival_timestamp":81480,"departure_time":"22:38:00","departure_timestamp":81480,"stop_id":"NB-0080-S","stop_sequence":70,"stop_headsign":null,"pickup_type":0,"drop_off_type":0,"continuous_pickup":null,"continuous_drop_off":null,"shape_dist_traveled":null,"timepoint":1,"stop_lat":42.281358,"stop_lon":-71.160065},{"id":1229400,"trip_id":"CR-508028-2615","arrival_time":"22:36:00","arrival_timestamp":81360,"departure_time":"22:36:00","departure_timestamp":81360,"stop_id":"NB-0076-S","stop_sequence":60,"stop_headsign":null,"pickup_type":0,"drop_off_type":0,"continuous_pickup":null,"continuous_drop_off":null,"shape_dist_traveled":null,"timepoint":1,"stop_lat":42.284969,"stop_lon":-71.153937},{"id":1229401,"trip_id":"CR-508028-2615","arrival_time":"22:34:00","arrival_timestamp":81240,"departure_time":"22:34:00","departure_timestamp":81240,"stop_id":"NB-0072-S","stop_sequence":50,"stop_headsign":null,"pickup_type":0,"drop_off_type":0,"continuous_pickup":null,"continuous_drop_off":null,"shape_dist_traveled":null,"timepoint":1,"stop_lat":42.286588,"stop_lon":-71.145557},{"id":1229402,"trip_id":"CR-508028-2615","arrival_time":"22:31:00","arrival_timestamp":81060,"departure_time":"22:31:00","departure_timestamp":81060,"stop_id":"NB-0064-S","stop_sequence":40,"stop_headsign":null,"pickup_type":0,"drop_off_type":0,"continuous_pickup":null,"continuous_drop_off":null,"shape_dist_traveled":null,"timepoint":1,"stop_lat":42.287442,"stop_lon":-71.130283},{"id":1229403,"trip_id":"CR-508028-2615","arrival_time":"22:28:00","arrival_timestamp":80880,"departure_time":"22:28:00","departure_timestamp":80880,"stop_id":"NEC-2237","stop_sequence":30,"stop_headsign":null,"pickup_type":0,"drop_off_type":0,"continuous_pickup":null,"continuous_drop_off":null,"shape_dist_traveled":null,"timepoint":1,"stop_lat":42.300522,"stop_lon":-71.113686},{"id":1229404,"trip_id":"CR-508028-2615","arrival_time":"22:23:00","arrival_timestamp":80580,"departure_time":"22:23:00","departure_timestamp":80580,"stop_id":"NEC-2265","stop_sequence":20,"stop_headsign":null,"pickup_type":0,"drop_off_type":0,"continuous_pickup":null,"continuous_drop_off":null,"shape_dist_traveled":null,"timepoint":1,"stop_lat":42.336608,"stop_lon":-71.089208},{"id":1229405,"trip_id":"CR-508028-2615","arrival_time":"22:20:00","arrival_timestamp":80400,"departure_time":"22:20:00","departure_timestamp":80400,"stop_id":"NEC-2276","stop_sequence":10,"stop_headsign":null,"pickup_type":0,"drop_off_type":0,"continuous_pickup":null,"continuous_drop_off":null,"shape_dist_traveled":null,"timepoint":1,"stop_lat":42.34735,"stop_lon":-71.075727},{"id":1229406,"trip_id":"CR-508028-2615","arrival_time":"22:15:00","arrival_timestamp":80100,"departure_time":"22:15:00","departure_timestamp":80100,"stop_id":"NEC-2287","stop_sequence":0,"stop_headsign":null,"pickup_type":0,"drop_off_type":1,"continuous_pickup":null,"continuous_drop_off":null,"shape_dist_traveled":null,"timepoint":1,"stop_lat":42.35141,"stop_lon":-71.055417}]},{"trip_id":"CR-501368-2601","route_id":"CR-Needham","service_id":"FLL 21-S-Su-1-S0f","trip_headsign":"Needham Heights","trip_short_name":"2601","direction_id":0,"block_id":null,"shape_id":"9860002","wheelchair_accessible":1,"bikes_allowed":1,"stop_times":[{"id":1221913,"trip_id":"CR-501368-2601","arrival_time":"07:15:00","arrival_timestamp":26100,"departure_time":"07:15:00","departure_timestamp":26100,"stop_id":"NEC-2287","stop_sequence":0,"stop_headsign":null,"pickup_type":0,"drop_off_type":1,"continuous_pickup":null,"continuous_drop_off":null,"shape_dist_traveled":null,"timepoint":1,"stop_lat":42.35141,"stop_lon":-71.055417},{"id":1222010,"trip_id":"CR-501368-2601","arrival_time":"07:55:00","arrival_timestamp":28500,"departure_time":"07:55:00","departure_timestamp":28500,"stop_id":"NB-0137-S","stop_sequence":110,"stop_headsign":null,"pickup_type":1,"drop_off_type":0,"continuous_pickup":null,"continuous_drop_off":null,"shape_dist_traveled":null,"timepoint":1,"stop_lat":42.293444,"stop_lon":-71.236027},{"id":1222011,"trip_id":"CR-501368-2601","arrival_time":"07:50:00","arrival_timestamp":28200,"departure_time":"07:50:00","departure_timestamp":28200,"stop_id":"NB-0127-S","stop_sequence":100,"stop_headsign":null,"pickup_type":0,"drop_off_type":0,"continuous_pickup":null,"continuous_drop_off":null,"shape_dist_traveled":null,"timepoint":1,"stop_lat":42.280775,"stop_lon":-71.237686},{"id":1222012,"trip_id":"CR-501368-2601","arrival_time":"07:46:00","arrival_timestamp":27960,"departure_time":"07:46:00","departure_timestamp":27960,"stop_id":"NB-0120-S","stop_sequence":90,"stop_headsign":null,"pickup_type":0,"drop_off_type":0,"continuous_pickup":null,"continuous_drop_off":null,"shape_dist_traveled":null,"timepoint":1,"stop_lat":42.273187,"stop_lon":-71.235559},{"id":1222013,"trip_id":"CR-501368-2601","arrival_time":"07:43:00","arrival_timestamp":27780,"departure_time":"07:43:00","departure_timestamp":27780,"stop_id":"NB-0109-S","stop_sequence":80,"stop_headsign":null,"pickup_type":0,"drop_off_type":0,"continuous_pickup":null,"continuous_drop_off":null,"shape_dist_traveled":null,"timepoint":1,"stop_lat":42.275648,"stop_lon":-71.215528},{"id":1222014,"trip_id":"CR-501368-2601","arrival_time":"07:38:00","arrival_timestamp":27480,"departure_time":"07:38:00","departure_timestamp":27480,"stop_id":"NB-0080-S","stop_sequence":70,"stop_headsign":null,"pickup_type":0,"drop_off_type":0,"continuous_pickup":null,"continuous_drop_off":null,"shape_dist_traveled":null,"timepoint":1,"stop_lat":42.281358,"stop_lon":-71.160065},{"id":1222015,"trip_id":"CR-501368-2601","arrival_time":"07:36:00","arrival_timestamp":27360,"departure_time":"07:36:00","departure_timestamp":27360,"stop_id":"NB-0076-S","stop_sequence":60,"stop_headsign":null,"pickup_type":0,"drop_off_type":0,"continuous_pickup":null,"continuous_drop_off":null,"shape_dist_traveled":null,"timepoint":1,"stop_lat":42.284969,"stop_lon":-71.153937},{"id":1222016,"trip_id":"CR-501368-2601","arrival_time":"07:34:00","arrival_timestamp":27240,"departure_time":"07:34:00","departure_timestamp":27240,"stop_id":"NB-0072-S","stop_sequence":50,"stop_headsign":null,"pickup_type":0,"drop_off_type":0,"continuous_pickup":null,"continuous_drop_off":null,"shape_dist_traveled":null,"timepoint":1,"stop_lat":42.286588,"stop_lon":-71.145557},{"id":1222017,"trip_id":"CR-501368-2601","arrival_time":"07:31:00","arrival_timestamp":27060,"departure_time":"07:31:00","departure_timestamp":27060,"stop_id":"NB-0064-S","stop_sequence":40,"stop_headsign":null,"pickup_type":0,"drop_off_type":0,"continuous_pickup":null,"continuous_drop_off":null,"shape_dist_traveled":null,"timepoint":1,"stop_lat":42.287442,"stop_lon":-71.130283},{"id":1222018,"trip_id":"CR-501368-2601","arrival_time":"07:28:00","arrival_timestamp":26880,"departure_time":"07:28:00","departure_timestamp":26880,"stop_id":"NEC-2237","stop_sequence":30,"stop_headsign":null,"pickup_type":0,"drop_off_type":0,"continuous_pickup":null,"continuous_drop_off":null,"shape_dist_traveled":null,"timepoint":1,"stop_lat":42.300522,"stop_lon":-71.113686},{"id":1222019,"trip_id":"CR-501368-2601","arrival_time":"07:23:00","arrival_timestamp":26580,"departure_time":"07:23:00","departure_timestamp":26580,"stop_id":"NEC-2265","stop_sequence":20,"stop_headsign":null,"pickup_type":0,"drop_off_type":0,"continuous_pickup":null,"continuous_drop_off":null,"shape_dist_traveled":null,"timepoint":1,"stop_lat":42.336608,"stop_lon":-71.089208},{"id":1222020,"trip_id":"CR-501368-2601","arrival_time":"07:20:00","arrival_timestamp":26400,"departure_time":"07:20:00","departure_timestamp":26400,"stop_id":"NEC-2276","stop_sequence":10,"stop_headsign":null,"pickup_type":0,"drop_off_type":0,"continuous_pickup":null,"continuous_drop_off":null,"shape_dist_traveled":null,"timepoint":1,"stop_lat":42.34735,"stop_lon":-71.075727}]},{"trip_id":"CR-501367-2603","route_id":"CR-Needham","service_id":"FLL 21-S-Su-1-S0f","trip_headsign":"Needham Heights","trip_short_name":"2603","direction_id":0,"block_id":null,"shape_id":"9860002","wheelchair_accessible":1,"bikes_allowed":1,"stop_times":[{"id":1221914,"trip_id":"CR-501367-2603","arrival_time":"09:55:00","arrival_timestamp":35700,"departure_time":"09:55:00","departure_timestamp":35700,"stop_id":"NB-0137-S","stop_sequence":110,"stop_headsign":null,"pickup_type":1,"drop_off_type":0,"continuous_pickup":null,"continuous_drop_off":null,"shape_dist_traveled":null,"timepoint":1,"stop_lat":42.293444,"stop_lon":-71.236027},{"id":1221915,"trip_id":"CR-501367-2603","arrival_time":"09:50:00","arrival_timestamp":35400,"departure_time":"09:50:00","departure_timestamp":35400,"stop_id":"NB-0127-S","stop_sequence":100,"stop_headsign":null,"pickup_type":0,"drop_off_type":0,"continuous_pickup":null,"continuous_drop_off":null,"shape_dist_traveled":null,"timepoint":1,"stop_lat":42.280775,"stop_lon":-71.237686},{"id":1221916,"trip_id":"CR-501367-2603","arrival_time":"09:46:00","arrival_timestamp":35160,"departure_time":"09:46:00","departure_timestamp":35160,"stop_id":"NB-0120-S","stop_sequence":90,"stop_headsign":null,"pickup_type":0,"drop_off_type":0,"continuous_pickup":null,"continuous_drop_off":null,"shape_dist_traveled":null,"timepoint":1,"stop_lat":42.273187,"stop_lon":-71.235559},{"id":1221917,"trip_id":"CR-501367-2603","arrival_time":"09:43:00","arrival_timestamp":34980,"departure_time":"09:43:00","departure_timestamp":34980,"stop_id":"NB-0109-S","stop_sequence":80,"stop_headsign":null,"pickup_type":0,"drop_off_type":0,"continuous_pickup":null,"continuous_drop_off":null,"shape_dist_traveled":null,"timepoint":1,"stop_lat":42.275648,"stop_lon":-71.215528},{"id":1221918,"trip_id":"CR-501367-2603","arrival_time":"09:38:00","arrival_timestamp":34680,"departure_time":"09:38:00","departure_timestamp":34680,"stop_id":"NB-0080-S","stop_sequence":70,"stop_headsign":null,"pickup_type":0,"drop_off_type":0,"continuous_pickup":null,"continuous_drop_off":null,"shape_dist_traveled":null,"timepoint":1,"stop_lat":42.281358,"stop_lon":-71.160065},{"id":1221919,"trip_id":"CR-501367-2603","arrival_time":"09:36:00","arrival_timestamp":34560,"departure_time":"09:36:00","departure_timestamp":34560,"stop_id":"NB-0076-S","stop_sequence":60,"stop_headsign":null,"pickup_type":0,"drop_off_type":0,"continuous_pickup":null,"continuous_drop_off":null,"shape_dist_traveled":null,"timepoint":1,"stop_lat":42.284969,"stop_lon":-71.153937},{"id":1221920,"trip_id":"CR-501367-2603","arrival_time":"09:34:00","arrival_timestamp":34440,"departure_time":"09:34:00","departure_timestamp":34440,"stop_id":"NB-0072-S","stop_sequence":50,"stop_headsign":null,"pickup_type":0,"drop_off_type":0,"continuous_pickup":null,"continuous_drop_off":null,"shape_dist_traveled":null,"timepoint":1,"stop_lat":42.286588,"stop_lon":-71.145557},{"id":1221921,"trip_id":"CR-501367-2603","arrival_time":"09:31:00","arrival_timestamp":34260,"departure_time":"09:31:00","departure_timestamp":34260,"stop_id":"NB-0064-S","stop_sequence":40,"stop_headsign":null,"pickup_type":0,"drop_off_type":0,"continuous_pickup":null,"continuous_drop_off":null,"shape_dist_traveled":null,"timepoint":1,"stop_lat":42.287442,"stop_lon":-71.130283},{"id":1221922,"trip_id":"CR-501367-2603","arrival_time":"09:28:00","arrival_timestamp":34080,"departure_time":"09:28:00","departure_timestamp":34080,"stop_id":"NEC-2237","stop_sequence":30,"stop_headsign":null,"pickup_type":0,"drop_off_type":0,"continuous_pickup":null,"continuous_drop_off":null,"shape_dist_traveled":null,"timepoint":1,"stop_lat":42.300522,"stop_lon":-71.113686},{"id":1221923,"trip_id":"CR-501367-2603","arrival_time":"09:23:00","arrival_timestamp":33780,"departure_time":"09:23:00","departure_timestamp":33780,"stop_id":"NEC-2265","stop_sequence":20,"stop_headsign":null,"pickup_type":0,"drop_off_type":0,"continuous_pickup":null,"continuous_drop_off":null,"shape_dist_traveled":null,"timepoint":1,"stop_lat":42.336608,"stop_lon":-71.089208},{"id":1221924,"trip_id":"CR-501367-2603","arrival_time":"09:20:00","arrival_timestamp":33600,"departure_time":"09:20:00","departure_timestamp":33600,"stop_id":"NEC-2276","stop_sequence":10,"stop_headsign":null,"pickup_type":0,"drop_off_type":0,"continuous_pickup":null,"continuous_drop_off":null,"shape_dist_traveled":null,"timepoint":1,"stop_lat":42.34735,"stop_lon":-71.075727},{"id":1221925,"trip_id":"CR-501367-2603","arrival_time":"09:15:00","arrival_timestamp":33300,"departure_time":"09:15:00","departure_timestamp":33300,"stop_id":"NEC-2287","stop_sequence":0,"stop_headsign":null,"pickup_type":0,"drop_off_type":1,"continuous_pickup":null,"continuous_drop_off":null,"shape_dist_traveled":null,"timepoint":1,"stop_lat":42.35141,"stop_lon":-71.055417}]},{"trip_id":"CR-501365-2605","route_id":"CR-Needham","service_id":"FLL 21-S-Su-1-S0f","trip_headsign":"Needham Heights","trip_short_name":"2605","direction_id":0,"block_id":null,"shape_id":"9860002","wheelchair_accessible":1,"bikes_allowed":1,"stop_times":[{"id":1221938,"trip_id":"CR-501365-2605","arrival_time":"11:55:00","arrival_timestamp":42900,"departure_time":"11:55:00","departure_timestamp":42900,"stop_id":"NB-0137-S","stop_sequence":110,"stop_headsign":null,"pickup_type":1,"drop_off_type":0,"continuous_pickup":null,"continuous_drop_off":null,"shape_dist_traveled":null,"timepoint":1,"stop_lat":42.293444,"stop_lon":-71.236027},{"id":1221939,"trip_id":"CR-501365-2605","arrival_time":"11:50:00","arrival_timestamp":42600,"departure_time":"11:50:00","departure_timestamp":42600,"stop_id":"NB-0127-S","stop_sequence":100,"stop_headsign":null,"pickup_type":0,"drop_off_type":0,"continuous_pickup":null,"continuous_drop_off":null,"shape_dist_traveled":null,"timepoint":1,"stop_lat":42.280775,"stop_lon":-71.237686},{"id":1221940,"trip_id":"CR-501365-2605","arrival_time":"11:46:00","arrival_timestamp":42360,"departure_time":"11:46:00","departure_timestamp":42360,"stop_id":"NB-0120-S","stop_sequence":90,"stop_headsign":null,"pickup_type":0,"drop_off_type":0,"continuous_pickup":null,"continuous_drop_off":null,"shape_dist_traveled":null,"timepoint":1,"stop_lat":42.273187,"stop_lon":-71.235559},{"id":1221941,"trip_id":"CR-501365-2605","arrival_time":"11:43:00","arrival_timestamp":42180,"departure_time":"11:43:00","departure_timestamp":42180,"stop_id":"NB-0109-S","stop_sequence":80,"stop_headsign":null,"pickup_type":0,"drop_off_type":0,"continuous_pickup":null,"continuous_drop_off":null,"shape_dist_traveled":null,"timepoint":1,"stop_lat":42.275648,"stop_lon":-71.215528},{"id":1221942,"trip_id":"CR-501365-2605","arrival_time":"11:38:00","arrival_timestamp":41880,"departure_time":"11:38:00","departure_timestamp":41880,"stop_id":"NB-0080-S","stop_sequence":70,"stop_headsign":null,"pickup_type":0,"drop_off_type":0,"continuous_pickup":null,"continuous_drop_off":null,"shape_dist_traveled":null,"timepoint":1,"stop_lat":42.281358,"stop_lon":-71.160065},{"id":1221943,"trip_id":"CR-501365-2605","arrival_time":"11:36:00","arrival_timestamp":41760,"departure_time":"11:36:00","departure_timestamp":41760,"stop_id":"NB-0076-S","stop_sequence":60,"stop_headsign":null,"pickup_type":0,"drop_off_type":0,"continuous_pickup":null,"continuous_drop_off":null,"shape_dist_traveled":null,"timepoint":1,"stop_lat":42.284969,"stop_lon":-71.153937},{"id":1221944,"trip_id":"CR-501365-2605","arrival_time":"11:34:00","arrival_timestamp":41640,"departure_time":"11:34:00","departure_timestamp":41640,"stop_id":"NB-0072-S","stop_sequence":50,"stop_headsign":null,"pickup_type":0,"drop_off_type":0,"continuous_pickup":null,"continuous_drop_off":null,"shape_dist_traveled":null,"timepoint":1,"stop_lat":42.286588,"stop_lon":-71.145557},{"id":1221945,"trip_id":"CR-501365-2605","arrival_time":"11:31:00","arrival_timestamp":41460,"departure_time":"11:31:00","departure_timestamp":41460,"stop_id":"NB-0064-S","stop_sequence":40,"stop_headsign":null,"pickup_type":0,"drop_off_type":0,"continuous_pickup":null,"continuous_drop_off":null,"shape_dist_traveled":null,"timepoint":1,"stop_lat":42.287442,"stop_lon":-71.130283},{"id":1221946,"trip_id":"CR-501365-2605","arrival_time":"11:28:00","arrival_timestamp":41280,"departure_time":"11:28:00","departure_timestamp":41280,"stop_id":"NEC-2237","stop_sequence":30,"stop_headsign":null,"pickup_type":0,"drop_off_type":0,"continuous_pickup":null,"continuous_drop_off":null,"shape_dist_traveled":null,"timepoint":1,"stop_lat":42.300522,"stop_lon":-71.113686},{"id":1221947,"trip_id":"CR-501365-2605","arrival_time":"11:23:00","arrival_timestamp":40980,"departure_time":"11:23:00","departure_timestamp":40980,"stop_id":"NEC-2265","stop_sequence":20,"stop_headsign":null,"pickup_type":0,"drop_off_type":0,"continuous_pickup":null,"continuous_drop_off":null,"shape_dist_traveled":null,"timepoint":1,"stop_lat":42.336608,"stop_lon":-71.089208},{"id":1221948,"trip_id":"CR-501365-2605","arrival_time":"11:20:00","arrival_timestamp":40800,"departure_time":"11:20:00","departure_timestamp":40800,"stop_id":"NEC-2276","stop_sequence":10,"stop_headsign":null,"pickup_type":0,"drop_off_type":0,"continuous_pickup":null,"continuous_drop_off":null,"shape_dist_traveled":null,"timepoint":1,"stop_lat":42.34735,"stop_lon":-71.075727},{"id":1221949,"trip_id":"CR-501365-2605","arrival_time":"11:15:00","arrival_timestamp":40500,"departure_time":"11:15:00","departure_timestamp":40500,"stop_id":"NEC-2287","stop_sequence":0,"stop_headsign":null,"pickup_type":0,"drop_off_type":1,"continuous_pickup":null,"continuous_drop_off":null,"shape_dist_traveled":null,"timepoint":1,"stop_lat":42.35141,"stop_lon":-71.055417}]},{"trip_id":"CR-501363-2607","route_id":"CR-Needham","service_id":"FLL 21-S-Su-1-S0f","trip_headsign":"Needham Heights","trip_short_name":"2607","direction_id":0,"block_id":null,"shape_id":"9860002","wheelchair_accessible":1,"bikes_allowed":1,"stop_times":[{"id":1221859,"trip_id":"CR-501363-2607","arrival_time":"13:36:00","arrival_timestamp":48960,"departure_time":"13:36:00","departure_timestamp":48960,"stop_id":"NB-0076-S","stop_sequence":60,"stop_headsign":null,"pickup_type":0,"drop_off_type":0,"continuous_pickup":null,"continuous_drop_off":null,"shape_dist_traveled":null,"timepoint":1,"stop_lat":42.284969,"stop_lon":-71.153937},{"id":1221860,"trip_id":"CR-501363-2607","arrival_time":"13:34:00","arrival_timestamp":48840,"departure_time":"13:34:00","departure_timestamp":48840,"stop_id":"NB-0072-S","stop_sequence":50,"stop_headsign":null,"pickup_type":0,"drop_off_type":0,"continuous_pickup":null,"continuous_drop_off":null,"shape_dist_traveled":null,"timepoint":1,"stop_lat":42.286588,"stop_lon":-71.145557},{"id":1221861,"trip_id":"CR-501363-2607","arrival_time":"13:31:00","arrival_timestamp":48660,"departure_time":"13:31:00","departure_timestamp":48660,"stop_id":"NB-0064-S","stop_sequence":40,"stop_headsign":null,"pickup_type":0,"drop_off_type":0,"continuous_pickup":null,"continuous_drop_off":null,"shape_dist_traveled":null,"timepoint":1,"stop_lat":42.287442,"stop_lon":-71.130283},{"id":1221862,"trip_id":"CR-501363-2607","arrival_time":"13:28:00","arrival_timestamp":48480,"departure_time":"13:28:00","departure_timestamp":48480,"stop_id":"NEC-2237","stop_sequence":30,"stop_headsign":null,"pickup_type":0,"drop_off_type":0,"continuous_pickup":null,"continuous_drop_off":null,"shape_dist_traveled":null,"timepoint":1,"stop_lat":42.300522,"stop_lon":-71.113686},{"id":1221863,"trip_id":"CR-501363-2607","arrival_time":"13:23:00","arrival_timestamp":48180,"departure_time":"13:23:00","departure_timestamp":48180,"stop_id":"NEC-2265","stop_sequence":20,"stop_headsign":null,"pickup_type":0,"drop_off_type":0,"continuous_pickup":null,"continuous_drop_off":null,"shape_dist_traveled":null,"timepoint":1,"stop_lat":42.336608,"stop_lon":-71.089208},{"id":1221864,"trip_id":"CR-501363-2607","arrival_time":"13:20:00","arrival_timestamp":48000,"departure_time":"13:20:00","departure_timestamp":48000,"stop_id":"NEC-2276","stop_sequence":10,"stop_headsign":null,"pickup_type":0,"drop_off_type":0,"continuous_pickup":null,"continuous_drop_off":null,"shape_dist_traveled":null,"timepoint":1,"stop_lat":42.34735,"stop_lon":-71.075727},{"id":1221865,"trip_id":"CR-501363-2607","arrival_time":"13:15:00","arrival_timestamp":47700,"departure_time":"13:15:00","departure_timestamp":47700,"stop_id":"NEC-2287","stop_sequence":0,"stop_headsign":null,"pickup_type":0,"drop_off_type":1,"continuous_pickup":null,"continuous_drop_off":null,"shape_dist_traveled":null,"timepoint":1,"stop_lat":42.35141,"stop_lon":-71.055417},{"id":1221962,"trip_id":"CR-501363-2607","arrival_time":"13:55:00","arrival_timestamp":50100,"departure_time":"13:55:00","departure_timestamp":50100,"stop_id":"NB-0137-S","stop_sequence":110,"stop_headsign":null,"pickup_type":1,"drop_off_type":0,"continuous_pickup":null,"continuous_drop_off":null,"shape_dist_traveled":null,"timepoint":1,"stop_lat":42.293444,"stop_lon":-71.236027},{"id":1221963,"trip_id":"CR-501363-2607","arrival_time":"13:50:00","arrival_timestamp":49800,"departure_time":"13:50:00","departure_timestamp":49800,"stop_id":"NB-0127-S","stop_sequence":100,"stop_headsign":null,"pickup_type":0,"drop_off_type":0,"continuous_pickup":null,"continuous_drop_off":null,"shape_dist_traveled":null,"timepoint":1,"stop_lat":42.280775,"stop_lon":-71.237686},{"id":1221964,"trip_id":"CR-501363-2607","arrival_time":"13:46:00","arrival_timestamp":49560,"departure_time":"13:46:00","departure_timestamp":49560,"stop_id":"NB-0120-S","stop_sequence":90,"stop_headsign":null,"pickup_type":0,"drop_off_type":0,"continuous_pickup":null,"continuous_drop_off":null,"shape_dist_traveled":null,"timepoint":1,"stop_lat":42.273187,"stop_lon":-71.235559},{"id":1221965,"trip_id":"CR-501363-2607","arrival_time":"13:43:00","arrival_timestamp":49380,"departure_time":"13:43:00","departure_timestamp":49380,"stop_id":"NB-0109-S","stop_sequence":80,"stop_headsign":null,"pickup_type":0,"drop_off_type":0,"continuous_pickup":null,"continuous_drop_off":null,"shape_dist_traveled":null,"timepoint":1,"stop_lat":42.275648,"stop_lon":-71.215528},{"id":1221966,"trip_id":"CR-501363-2607","arrival_time":"13:38:00","arrival_timestamp":49080,"departure_time":"13:38:00","departure_timestamp":49080,"stop_id":"NB-0080-S","stop_sequence":70,"stop_headsign":null,"pickup_type":0,"drop_off_type":0,"continuous_pickup":null,"continuous_drop_off":null,"shape_dist_traveled":null,"timepoint":1,"stop_lat":42.281358,"stop_lon":-71.160065}]},{"trip_id":"CR-501361-2613","route_id":"CR-Needham","service_id":"FLL 21-S-Su-1-S0f","trip_headsign":"Needham Heights","trip_short_name":"2613","direction_id":0,"block_id":null,"shape_id":"9860002","wheelchair_accessible":1,"bikes_allowed":1,"stop_times":[{"id":1221878,"trip_id":"CR-501361-2613","arrival_time":"19:55:00","arrival_timestamp":71700,"departure_time":"19:55:00","departure_timestamp":71700,"stop_id":"NB-0137-S","stop_sequence":110,"stop_headsign":null,"pickup_type":1,"drop_off_type":0,"continuous_pickup":null,"continuous_drop_off":null,"shape_dist_traveled":null,"timepoint":1,"stop_lat":42.293444,"stop_lon":-71.236027},{"id":1221879,"trip_id":"CR-501361-2613","arrival_time":"19:50:00","arrival_timestamp":71400,"departure_time":"19:50:00","departure_timestamp":71400,"stop_id":"NB-0127-S","stop_sequence":100,"stop_headsign":null,"pickup_type":0,"drop_off_type":0,"continuous_pickup":null,"continuous_drop_off":null,"shape_dist_traveled":null,"timepoint":1,"stop_lat":42.280775,"stop_lon":-71.237686},{"id":1221880,"trip_id":"CR-501361-2613","arrival_time":"19:46:00","arrival_timestamp":71160,"departure_time":"19:46:00","departure_timestamp":71160,"stop_id":"NB-0120-S","stop_sequence":90,"stop_headsign":null,"pickup_type":0,"drop_off_type":0,"continuous_pickup":null,"continuous_drop_off":null,"shape_dist_traveled":null,"timepoint":1,"stop_lat":42.273187,"stop_lon":-71.235559},{"id":1221881,"trip_id":"CR-501361-2613","arrival_time":"19:43:00","arrival_timestamp":70980,"departure_time":"19:43:00","departure_timestamp":70980,"stop_id":"NB-0109-S","stop_sequence":80,"stop_headsign":null,"pickup_type":0,"drop_off_type":0,"continuous_pickup":null,"continuous_drop_off":null,"shape_dist_traveled":null,"timepoint":1,"stop_lat":42.275648,"stop_lon":-71.215528},{"id":1221882,"trip_id":"CR-501361-2613","arrival_time":"19:38:00","arrival_timestamp":70680,"departure_time":"19:38:00","departure_timestamp":70680,"stop_id":"NB-0080-S","stop_sequence":70,"stop_headsign":null,"pickup_type":0,"drop_off_type":0,"continuous_pickup":null,"continuous_drop_off":null,"shape_dist_traveled":null,"timepoint":1,"stop_lat":42.281358,"stop_lon":-71.160065},{"id":1221883,"trip_id":"CR-501361-2613","arrival_time":"19:36:00","arrival_timestamp":70560,"departure_time":"19:36:00","departure_timestamp":70560,"stop_id":"NB-0076-S","stop_sequence":60,"stop_headsign":null,"pickup_type":0,"drop_off_type":0,"continuous_pickup":null,"continuous_drop_off":null,"shape_dist_traveled":null,"timepoint":1,"stop_lat":42.284969,"stop_lon":-71.153937},{"id":1221884,"trip_id":"CR-501361-2613","arrival_time":"19:34:00","arrival_timestamp":70440,"departure_time":"19:34:00","departure_timestamp":70440,"stop_id":"NB-0072-S","stop_sequence":50,"stop_headsign":null,"pickup_type":0,"drop_off_type":0,"continuous_pickup":null,"continuous_drop_off":null,"shape_dist_traveled":null,"timepoint":1,"stop_lat":42.286588,"stop_lon":-71.145557},{"id":1221885,"trip_id":"CR-501361-2613","arrival_time":"19:31:00","arrival_timestamp":70260,"departure_time":"19:31:00","departure_timestamp":70260,"stop_id":"NB-0064-S","stop_sequence":40,"stop_headsign":null,"pickup_type":0,"drop_off_type":0,"continuous_pickup":null,"continuous_drop_off":null,"shape_dist_traveled":null,"timepoint":1,"stop_lat":42.287442,"stop_lon":-71.130283},{"id":1221886,"trip_id":"CR-501361-2613","arrival_time":"19:28:00","arrival_timestamp":70080,"departure_time":"19:28:00","departure_timestamp":70080,"stop_id":"NEC-2237","stop_sequence":30,"stop_headsign":null,"pickup_type":0,"drop_off_type":0,"continuous_pickup":null,"continuous_drop_off":null,"shape_dist_traveled":null,"timepoint":1,"stop_lat":42.300522,"stop_lon":-71.113686},{"id":1221887,"trip_id":"CR-501361-2613","arrival_time":"19:23:00","arrival_timestamp":69780,"departure_time":"19:23:00","departure_timestamp":69780,"stop_id":"NEC-2265","stop_sequence":20,"stop_headsign":null,"pickup_type":0,"drop_off_type":0,"continuous_pickup":null,"continuous_drop_off":null,"shape_dist_traveled":null,"timepoint":1,"stop_lat":42.336608,"stop_lon":-71.089208},{"id":1221888,"trip_id":"CR-501361-2613","arrival_time":"19:20:00","arrival_timestamp":69600,"departure_time":"19:20:00","departure_timestamp":69600,"stop_id":"NEC-2276","stop_sequence":10,"stop_headsign":null,"pickup_type":0,"drop_off_type":0,"continuous_pickup":null,"continuous_drop_off":null,"shape_dist_traveled":null,"timepoint":1,"stop_lat":42.34735,"stop_lon":-71.075727},{"id":1221889,"trip_id":"CR-501361-2613","arrival_time":"19:15:00","arrival_timestamp":69300,"departure_time":"19:15:00","departure_timestamp":69300,"stop_id":"NEC-2287","stop_sequence":0,"stop_headsign":null,"pickup_type":0,"drop_off_type":1,"continuous_pickup":null,"continuous_drop_off":null,"shape_dist_traveled":null,"timepoint":1,"stop_lat":42.35141,"stop_lon":-71.055417}]},{"trip_id":"CR-501359-2611","route_id":"CR-Needham","service_id":"FLL 21-S-Su-1-S0f","trip_headsign":"Needham Heights","trip_short_name":"2611","direction_id":0,"block_id":null,"shape_id":"9860002","wheelchair_accessible":1,"bikes_allowed":1,"stop_times":[{"id":1221805,"trip_id":"CR-501359-2611","arrival_time":"17:15:00","arrival_timestamp":62100,"departure_time":"17:15:00","departure_timestamp":62100,"stop_id":"NEC-2287","stop_sequence":0,"stop_headsign":null,"pickup_type":0,"drop_off_type":1,"continuous_pickup":null,"continuous_drop_off":null,"shape_dist_traveled":null,"timepoint":1,"stop_lat":42.35141,"stop_lon":-71.055417},{"id":1221902,"trip_id":"CR-501359-2611","arrival_time":"17:55:00","arrival_timestamp":64500,"departure_time":"17:55:00","departure_timestamp":64500,"stop_id":"NB-0137-S","stop_sequence":110,"stop_headsign":null,"pickup_type":1,"drop_off_type":0,"continuous_pickup":null,"continuous_drop_off":null,"shape_dist_traveled":null,"timepoint":1,"stop_lat":42.293444,"stop_lon":-71.236027},{"id":1221903,"trip_id":"CR-501359-2611","arrival_time":"17:50:00","arrival_timestamp":64200,"departure_time":"17:50:00","departure_timestamp":64200,"stop_id":"NB-0127-S","stop_sequence":100,"stop_headsign":null,"pickup_type":0,"drop_off_type":0,"continuous_pickup":null,"continuous_drop_off":null,"shape_dist_traveled":null,"timepoint":1,"stop_lat":42.280775,"stop_lon":-71.237686},{"id":1221904,"trip_id":"CR-501359-2611","arrival_time":"17:46:00","arrival_timestamp":63960,"departure_time":"17:46:00","departure_timestamp":63960,"stop_id":"NB-0120-S","stop_sequence":90,"stop_headsign":null,"pickup_type":0,"drop_off_type":0,"continuous_pickup":null,"continuous_drop_off":null,"shape_dist_traveled":null,"timepoint":1,"stop_lat":42.273187,"stop_lon":-71.235559},{"id":1221905,"trip_id":"CR-501359-2611","arrival_time":"17:43:00","arrival_timestamp":63780,"departure_time":"17:43:00","departure_timestamp":63780,"stop_id":"NB-0109-S","stop_sequence":80,"stop_headsign":null,"pickup_type":0,"drop_off_type":0,"continuous_pickup":null,"continuous_drop_off":null,"shape_dist_traveled":null,"timepoint":1,"stop_lat":42.275648,"stop_lon":-71.215528},{"id":1221906,"trip_id":"CR-501359-2611","arrival_time":"17:38:00","arrival_timestamp":63480,"departure_time":"17:38:00","departure_timestamp":63480,"stop_id":"NB-0080-S","stop_sequence":70,"stop_headsign":null,"pickup_type":0,"drop_off_type":0,"continuous_pickup":null,"continuous_drop_off":null,"shape_dist_traveled":null,"timepoint":1,"stop_lat":42.281358,"stop_lon":-71.160065},{"id":1221907,"trip_id":"CR-501359-2611","arrival_time":"17:36:00","arrival_timestamp":63360,"departure_time":"17:36:00","departure_timestamp":63360,"stop_id":"NB-0076-S","stop_sequence":60,"stop_headsign":null,"pickup_type":0,"drop_off_type":0,"continuous_pickup":null,"continuous_drop_off":null,"shape_dist_traveled":null,"timepoint":1,"stop_lat":42.284969,"stop_lon":-71.153937},{"id":1221908,"trip_id":"CR-501359-2611","arrival_time":"17:34:00","arrival_timestamp":63240,"departure_time":"17:34:00","departure_timestamp":63240,"stop_id":"NB-0072-S","stop_sequence":50,"stop_headsign":null,"pickup_type":0,"drop_off_type":0,"continuous_pickup":null,"continuous_drop_off":null,"shape_dist_traveled":null,"timepoint":1,"stop_lat":42.286588,"stop_lon":-71.145557},{"id":1221909,"trip_id":"CR-501359-2611","arrival_time":"17:31:00","arrival_timestamp":63060,"departure_time":"17:31:00","departure_timestamp":63060,"stop_id":"NB-0064-S","stop_sequence":40,"stop_headsign":null,"pickup_type":0,"drop_off_type":0,"continuous_pickup":null,"continuous_drop_off":null,"shape_dist_traveled":null,"timepoint":1,"stop_lat":42.287442,"stop_lon":-71.130283},{"id":1221910,"trip_id":"CR-501359-2611","arrival_time":"17:28:00","arrival_timestamp":62880,"departure_time":"17:28:00","departure_timestamp":62880,"stop_id":"NEC-2237","stop_sequence":30,"stop_headsign":null,"pickup_type":0,"drop_off_type":0,"continuous_pickup":null,"continuous_drop_off":null,"shape_dist_traveled":null,"timepoint":1,"stop_lat":42.300522,"stop_lon":-71.113686},{"id":1221911,"trip_id":"CR-501359-2611","arrival_time":"17:23:00","arrival_timestamp":62580,"departure_time":"17:23:00","departure_timestamp":62580,"stop_id":"NEC-2265","stop_sequence":20,"stop_headsign":null,"pickup_type":0,"drop_off_type":0,"continuous_pickup":null,"continuous_drop_off":null,"shape_dist_traveled":null,"timepoint":1,"stop_lat":42.336608,"stop_lon":-71.089208},{"id":1221912,"trip_id":"CR-501359-2611","arrival_time":"17:20:00","arrival_timestamp":62400,"departure_time":"17:20:00","departure_timestamp":62400,"stop_id":"NEC-2276","stop_sequence":10,"stop_headsign":null,"pickup_type":0,"drop_off_type":0,"continuous_pickup":null,"continuous_drop_off":null,"shape_dist_traveled":null,"timepoint":1,"stop_lat":42.34735,"stop_lon":-71.075727}]},{"trip_id":"CR-501357-2609","route_id":"CR-Needham","service_id":"FLL 21-S-Su-1-S0f","trip_headsign":"Needham Heights","trip_short_name":"2609","direction_id":0,"block_id":null,"shape_id":"9860002","wheelchair_accessible":1,"bikes_allowed":1,"stop_times":[{"id":1221818,"trip_id":"CR-501357-2609","arrival_time":"15:55:00","arrival_timestamp":57300,"departure_time":"15:55:00","departure_timestamp":57300,"stop_id":"NB-0137-S","stop_sequence":110,"stop_headsign":null,"pickup_type":1,"drop_off_type":0,"continuous_pickup":null,"continuous_drop_off":null,"shape_dist_traveled":null,"timepoint":1,"stop_lat":42.293444,"stop_lon":-71.236027},{"id":1221819,"trip_id":"CR-501357-2609","arrival_time":"15:50:00","arrival_timestamp":57000,"departure_time":"15:50:00","departure_timestamp":57000,"stop_id":"NB-0127-S","stop_sequence":100,"stop_headsign":null,"pickup_type":0,"drop_off_type":0,"continuous_pickup":null,"continuous_drop_off":null,"shape_dist_traveled":null,"timepoint":1,"stop_lat":42.280775,"stop_lon":-71.237686},{"id":1221820,"trip_id":"CR-501357-2609","arrival_time":"15:46:00","arrival_timestamp":56760,"departure_time":"15:46:00","departure_timestamp":56760,"stop_id":"NB-0120-S","stop_sequence":90,"stop_headsign":null,"pickup_type":0,"drop_off_type":0,"continuous_pickup":null,"continuous_drop_off":null,"shape_dist_traveled":null,"timepoint":1,"stop_lat":42.273187,"stop_lon":-71.235559},{"id":1221821,"trip_id":"CR-501357-2609","arrival_time":"15:43:00","arrival_timestamp":56580,"departure_time":"15:43:00","departure_timestamp":56580,"stop_id":"NB-0109-S","stop_sequence":80,"stop_headsign":null,"pickup_type":0,"drop_off_type":0,"continuous_pickup":null,"continuous_drop_off":null,"shape_dist_traveled":null,"timepoint":1,"stop_lat":42.275648,"stop_lon":-71.215528},{"id":1221822,"trip_id":"CR-501357-2609","arrival_time":"15:38:00","arrival_timestamp":56280,"departure_time":"15:38:00","departure_timestamp":56280,"stop_id":"NB-0080-S","stop_sequence":70,"stop_headsign":null,"pickup_type":0,"drop_off_type":0,"continuous_pickup":null,"continuous_drop_off":null,"shape_dist_traveled":null,"timepoint":1,"stop_lat":42.281358,"stop_lon":-71.160065},{"id":1221823,"trip_id":"CR-501357-2609","arrival_time":"15:36:00","arrival_timestamp":56160,"departure_time":"15:36:00","departure_timestamp":56160,"stop_id":"NB-0076-S","stop_sequence":60,"stop_headsign":null,"pickup_type":0,"drop_off_type":0,"continuous_pickup":null,"continuous_drop_off":null,"shape_dist_traveled":null,"timepoint":1,"stop_lat":42.284969,"stop_lon":-71.153937},{"id":1221824,"trip_id":"CR-501357-2609","arrival_time":"15:34:00","arrival_timestamp":56040,"departure_time":"15:34:00","departure_timestamp":56040,"stop_id":"NB-0072-S","stop_sequence":50,"stop_headsign":null,"pickup_type":0,"drop_off_type":0,"continuous_pickup":null,"continuous_drop_off":null,"shape_dist_traveled":null,"timepoint":1,"stop_lat":42.286588,"stop_lon":-71.145557},{"id":1221825,"trip_id":"CR-501357-2609","arrival_time":"15:31:00","arrival_timestamp":55860,"departure_time":"15:31:00","departure_timestamp":55860,"stop_id":"NB-0064-S","stop_sequence":40,"stop_headsign":null,"pickup_type":0,"drop_off_type":0,"continuous_pickup":null,"continuous_drop_off":null,"shape_dist_traveled":null,"timepoint":1,"stop_lat":42.287442,"stop_lon":-71.130283},{"id":1221826,"trip_id":"CR-501357-2609","arrival_time":"15:28:00","arrival_timestamp":55680,"departure_time":"15:28:00","departure_timestamp":55680,"stop_id":"NEC-2237","stop_sequence":30,"stop_headsign":null,"pickup_type":0,"drop_off_type":0,"continuous_pickup":null,"continuous_drop_off":null,"shape_dist_traveled":null,"timepoint":1,"stop_lat":42.300522,"stop_lon":-71.113686},{"id":1221827,"trip_id":"CR-501357-2609","arrival_time":"15:23:00","arrival_timestamp":55380,"departure_time":"15:23:00","departure_timestamp":55380,"stop_id":"NEC-2265","stop_sequence":20,"stop_headsign":null,"pickup_type":0,"drop_off_type":0,"continuous_pickup":null,"continuous_drop_off":null,"shape_dist_traveled":null,"timepoint":1,"stop_lat":42.336608,"stop_lon":-71.089208},{"id":1221828,"trip_id":"CR-501357-2609","arrival_time":"15:20:00","arrival_timestamp":55200,"departure_time":"15:20:00","departure_timestamp":55200,"stop_id":"NEC-2276","stop_sequence":10,"stop_headsign":null,"pickup_type":0,"drop_off_type":0,"continuous_pickup":null,"continuous_drop_off":null,"shape_dist_traveled":null,"timepoint":1,"stop_lat":42.34735,"stop_lon":-71.075727},{"id":1221829,"trip_id":"CR-501357-2609","arrival_time":"15:15:00","arrival_timestamp":54900,"departure_time":"15:15:00","departure_timestamp":54900,"stop_id":"NEC-2287","stop_sequence":0,"stop_headsign":null,"pickup_type":0,"drop_off_type":1,"continuous_pickup":null,"continuous_drop_off":null,"shape_dist_traveled":null,"timepoint":1,"stop_lat":42.35141,"stop_lon":-71.055417}]}]}