{"route_id":"N","agency_id":"MTA NYCT","route_short_name":"N","route_long_name":"Broadway Local","route_desc":"Trains operate from Astoria-Ditmars Boulevard, Queens, to Stillwell Avenue, Brooklyn, at all times. N trains in Manhattan operate along Broadway and across the Manhattan Bridge to and from Brooklyn. Trains in Brooklyn operate along 4th Avenue, then through Borough Park and Gravesend. Trains typically operate local in Queens and express in Manhattan and Brooklyn. Late night trains operate local in Manhattan and to/from Brooklyn via Whitehall St, Manhattan. Weekends N trains operate local in Manhattan.","route_type":1,"route_url":"http://web.mta.info/nyct/service/pdf/tncur.pdf","route_color":"FCCC0A","route_text_color":null,"route_sort_order":null,"continuous_pickup":null,"continuous_drop_off":null,"trips":[]}